simplestructlogs/__init__.py
simplestructlogs/json_log_message.py
simplestructlogs/structured_logging.py
simplestructlogs/test_log.py
simplestructlogs-0.0.4.dist-info/LICENSE
simplestructlogs-0.0.4.dist-info/METADATA
simplestructlogs-0.0.4.dist-info/WHEEL
simplestructlogs-0.0.4.dist-info/top_level.txt
simplestructlogs-0.0.4.dist-info/RECORD
