Metadata-Version: 2.1
Name: simplestructlogs
Version: 0.0.4
Summary: A simple wrapper around the standard logging library to support structured logging.
Author-email: Calvin Echols <calvin@cechols.com>
Project-URL: Homepage, https://github.com/CalvinE/simplestructlogs-py
Project-URL: Bug Tracker, https://github.com/CalvinE/simplestructlogs-py/issues
Keywords: logging,structured,structured-logging
Classifier: Development Status :: 3 - Alpha
Classifier: Intended Audience :: Developers
Classifier: Programming Language :: Python :: 3
Classifier: License :: OSI Approved :: MIT License
Classifier: Operating System :: OS Independent
Requires-Python: >=3.8
License-File: LICENSE
